grumpy_tools/__init__.py
grumpy_tools/benchcmp.py
grumpy_tools/cli.py
grumpy_tools/coverparse.py
grumpy_tools/diffrange.py
grumpy_tools/genmake.py
grumpy_tools/grumpc.py
grumpy_tools/grumprun.py
grumpy_tools/grumpy_tools.py
grumpy_tools/pydeps.py
grumpy_tools/compiler/__init__.py
grumpy_tools/compiler/block.py
grumpy_tools/compiler/block_test.py
grumpy_tools/compiler/expr.py
grumpy_tools/compiler/expr_visitor.py
grumpy_tools/compiler/expr_visitor_test.py
grumpy_tools/compiler/imputil.py
grumpy_tools/compiler/imputil_test.py
grumpy_tools/compiler/shard_test.py
grumpy_tools/compiler/stmt.py
grumpy_tools/compiler/stmt_test.py
grumpy_tools/compiler/util.py
grumpy_tools/compiler/util_test.py
grumpy_tools/vendor/__init__.py
grumpy_tools/vendor/pythonparser/__init__.py
grumpy_tools/vendor/pythonparser/algorithm.py
grumpy_tools/vendor/pythonparser/ast.py
grumpy_tools/vendor/pythonparser/diagnostic.py
grumpy_tools/vendor/pythonparser/lexer.py
grumpy_tools/vendor/pythonparser/parser.py
grumpy_tools/vendor/pythonparser/source.py
grumpy_tools-0.1.0.dist-info/DESCRIPTION.rst
grumpy_tools-0.1.0.dist-info/METADATA
grumpy_tools-0.1.0.dist-info/RECORD
grumpy_tools-0.1.0.dist-info/WHEEL
grumpy_tools-0.1.0.dist-info/entry_points.txt
grumpy_tools-0.1.0.dist-info/metadata.json
grumpy_tools-0.1.0.dist-info/top_level.txt
