Metadata-Version: 2.0
Name: grumpy-tools
Version: 0.1.0
Summary: Grumpy Runtime & Transpiler
Home-page: https://github.com/google/grumpy
Author: Alan Justino et al.
Author-email: alan.justino@yahoo.com.br
License: Apache Software License 2.0
Keywords: grumpy_runtime
Platform: UNKNOWN
Classifier: Development Status :: 2 - Pre-Alpha
Classifier: Intended Audience :: Developers
Classifier: License :: OSI Approved :: Apache Software License
Classifier: Natural Language :: English
Classifier: Programming Language :: Python :: 2
Classifier: Programming Language :: Python :: 2.7
Requires-Python: ~=2.7.0
Requires-Dist: Click (>=6.0)
Requires-Dist: click-default-group (>=1.2)
Requires-Dist: importlib2 (>=3.5.0.2)
